jinja2_strcase/__init__.py
jinja2_strcase/jinja2_strcase.py
jinja2_strcase-0.0.2.dist-info/LICENSE
jinja2_strcase-0.0.2.dist-info/METADATA
jinja2_strcase-0.0.2.dist-info/WHEEL
jinja2_strcase-0.0.2.dist-info/top_level.txt
jinja2_strcase-0.0.2.dist-info/RECORD
